README.rst
setup.py
flytrap/__init__.py
flytrap/auth/__init__.py
flytrap/auth/urls.py
flytrap/auth/account/__init__.py
flytrap/auth/account/common/__init__.py
flytrap/auth/account/common/serizliers.py
flytrap/auth/account/common/views.py
flytrap/auth/account/session/__init__.py
flytrap/auth/account/token/__init__.py
flytrap/auth/account/token/auth.py
flytrap/auth/account/token/urls.py
flytrap/auth/account/token/views.py
flytrap_auth.egg-info/PKG-INFO
flytrap_auth.egg-info/SOURCES.txt
flytrap_auth.egg-info/dependency_links.txt
flytrap_auth.egg-info/requires.txt
flytrap_auth.egg-info/top_level.txt