Metadata-Version: 1.1
Name: flytrap-auth
Version: 0.0.6
Summary: A simple Django app to auth
Home-page: https://github.com/flytrap/flytrap-auth.git
Author: flytrap
Author-email: hiddenstat@gmail.com
License: UNKNOWN
Platform: UNKNOWN
Classifier: Development Status :: 4 - Beta
Classifier: Environment :: Web Environment
Classifier: Framework :: Django
Classifier: Intended Audience :: Developers
Classifier: License :: OSI Approved :: MIT License
Classifier: Operating System :: OS Independent
Classifier: Programming Language :: Python
Classifier: Programming Language :: Python :: 3
Classifier: Topic :: Software Development :: Libraries :: Python Modules
